nagisa_utils.cpython-314-x86_64-linux-musl.so
nagisa/__init__.py
nagisa/mecab_system_eval.py
nagisa/model.py
nagisa/nagisa_utils.c
nagisa/nagisa_utils.pyx
nagisa/prepro.py
nagisa/tagger.py
nagisa/train.py
nagisa/data/models.jpg
nagisa/data/nagisa_logo.png
nagisa/data/nagisa_v001.dict
nagisa/data/nagisa_v001.hp
nagisa/data/nagisa_v001.model
nagisa/data/sample_datasets/sample.dev
nagisa/data/sample_datasets/sample.dict
nagisa/data/sample_datasets/sample.emb
nagisa/data/sample_datasets/sample.pred
nagisa/data/sample_datasets/sample.test
nagisa/data/sample_datasets/sample.train
nagisa-0.2.11.dist-info/METADATA
nagisa-0.2.11.dist-info/WHEEL
nagisa-0.2.11.dist-info/top_level.txt
nagisa-0.2.11.dist-info/RECORD
nagisa-0.2.11.dist-info/licenses/LICENSE.txt
